dsnd_probability_cbarr/Binomialdistribution.py
dsnd_probability_cbarr/Gaussiandistribution.py
dsnd_probability_cbarr/Generaldistribution.py
dsnd_probability_cbarr/__init__.py
dsnd_probability_cbarr-1.1.dist-info/DESCRIPTION.rst
dsnd_probability_cbarr-1.1.dist-info/METADATA
dsnd_probability_cbarr-1.1.dist-info/RECORD
dsnd_probability_cbarr-1.1.dist-info/WHEEL
dsnd_probability_cbarr-1.1.dist-info/metadata.json
dsnd_probability_cbarr-1.1.dist-info/top_level.txt
