Metadata-Version: 2.0
Name: dsnd-probability-cbarr
Version: 1.1
Summary: Gaussian and Binomial distributions
Home-page: UNKNOWN
Author: Cindy Barrientos
Author-email: cbarrien@ucsd.edu
License: UNKNOWN
Platform: UNKNOWN
Classifier: Programming Language :: Python :: 3
Classifier: License :: OSI Approved :: MIT License
Classifier: Operating System :: OS Independent
